{
  "fio version" : "fio-3.28-261-gc3773-dirty",
  "timestamp" : 1648140301,
  "timestamp_ms" : 1648140301955,
  "time" : "Thu Mar 24 17:45:01 2022",
  "jobs" : [
    {
      "jobname" : "nvme2n2_mq-deadline_4Ki_iodepth-9",
      "groupid" : 0,
      "error" : 0,
      "eta" : 0,
      "elapsed" : 41,
      "job options" : {
        "name" : "nvme2n2_mq-deadline_4Ki_iodepth-9",
        "filename" : "/dev/nvme2n2",
        "direct" : "1",
        "size" : "107374182400",
        "ioengine" : "libaio",
        "zonemode" : "zbd",
        "rw" : "randread",
        "bs" : "4Ki",
        "runtime" : "30s",
        "numa_cpu_nodes" : "1",
        "ramp_time" : "10s",
        "iodepth" : "9",
        "percentile_list" : "50:95"
      },
      "read" : {
        "io_bytes" : 11456094208,
        "io_kbytes" : 11187592,
        "bw_bytes" : 381857078,
        "bw" : 372907,
        "iops" : 93226.559115,
        "runtime" : 30001,
        "total_ios" : 2796890,
        "short_ios" : 0,
        "drop_ios" : 0,
        "slat_ns" : {
          "min" : 1626,
          "max" : 53730,
          "mean" : 2519.918252,
          "stddev" : 734.470519,
          "N" : 2796890
        },
        "clat_ns" : {
          "min" : 12307,
          "max" : 701240,
          "mean" : 93236.358021,
          "stddev" : 19221.251130,
          "N" : 2796898,
          "percentile" : {
            "50.000000" : 88576,
            "95.000000" : 138240
          }
        },
        "lat_ns" : {
          "min" : 14672,
          "max" : 703161,
          "mean" : 95860.914282,
          "stddev" : 19202.530607,
          "N" : 2796898
        },
        "bw_min" : 366869,
        "bw_max" : 374160,
        "bw_agg" : 100.000000,
        "bw_mean" : 373199.533333,
        "bw_dev" : 935.786363,
        "bw_samples" : 60,
        "iops_min" : 91717,
        "iops_max" : 93540,
        "iops_mean" : 93299.683333,
        "iops_stddev" : 233.943966,
        "iops_samples" : 60
      },
      "write" : {
        "io_bytes" : 0,
        "io_kbytes" : 0,
        "bw_bytes" : 0,
        "bw" : 0,
        "iops" : 0.000000,
        "runtime" : 0,
        "total_ios" : 0,
        "short_ios" : 0,
        "drop_ios" : 0,
        "slat_ns" : {
          "min" : 0,
          "max" : 0,
          "mean" : 0.000000,
          "stddev" : 0.000000,
          "N" : 0
        },
        "clat_ns" : {
          "min" : 0,
          "max" : 0,
          "mean" : 0.000000,
          "stddev" : 0.000000,
          "N" : 0
        },
        "lat_ns" : {
          "min" : 0,
          "max" : 0,
          "mean" : 0.000000,
          "stddev" : 0.000000,
          "N" : 0
        },
        "bw_min" : 0,
        "bw_max" : 0,
        "bw_agg" : 0.000000,
        "bw_mean" : 0.000000,
        "bw_dev" : 0.000000,
        "bw_samples" : 0,
        "iops_min" : 0,
        "iops_max" : 0,
        "iops_mean" : 0.000000,
        "iops_stddev" : 0.000000,
        "iops_samples" : 0
      },
      "trim" : {
        "io_bytes" : 0,
        "io_kbytes" : 0,
        "bw_bytes" : 0,
        "bw" : 0,
        "iops" : 0.000000,
        "runtime" : 0,
        "total_ios" : 0,
        "short_ios" : 0,
        "drop_ios" : 0,
        "slat_ns" : {
          "min" : 0,
          "max" : 0,
          "mean" : 0.000000,
          "stddev" : 0.000000,
          "N" : 0
        },
        "clat_ns" : {
          "min" : 0,
          "max" : 0,
          "mean" : 0.000000,
          "stddev" : 0.000000,
          "N" : 0
        },
        "lat_ns" : {
          "min" : 0,
          "max" : 0,
          "mean" : 0.000000,
          "stddev" : 0.000000,
          "N" : 0
        },
        "bw_min" : 0,
        "bw_max" : 0,
        "bw_agg" : 0.000000,
        "bw_mean" : 0.000000,
        "bw_dev" : 0.000000,
        "bw_samples" : 0,
        "iops_min" : 0,
        "iops_max" : 0,
        "iops_mean" : 0.000000,
        "iops_stddev" : 0.000000,
        "iops_samples" : 0
      },
      "sync" : {
        "total_ios" : 0,
        "lat_ns" : {
          "min" : 0,
          "max" : 0,
          "mean" : 0.000000,
          "stddev" : 0.000000,
          "N" : 0
        }
      },
      "job_runtime" : 30000,
      "usr_cpu" : 14.306667,
      "sys_cpu" : 34.003333,
      "ctx" : 1450145,
      "majf" : 0,
      "minf" : 37,
      "iodepth_level" : {
        "1" : 0.000000,
        "2" : 0.000000,
        "4" : 0.000000,
        "8" : 100.000000,
        "16" : 0.000000,
        "32" : 0.000000,
        ">=64" : 0.000000
      },
      "iodepth_submit" : {
        "0" : 0.000000,
        "4" : 100.000000,
        "8" : 0.000000,
        "16" : 0.000000,
        "32" : 0.000000,
        "64" : 0.000000,
        ">=64" : 0.000000
      },
      "iodepth_complete" : {
        "0" : 0.000000,
        "4" : 99.999964,
        "8" : 0.100000,
        "16" : 0.000000,
        "32" : 0.000000,
        "64" : 0.000000,
        ">=64" : 0.000000
      },
      "latency_ns" : {
        "2" : 0.000000,
        "4" : 0.000000,
        "10" : 0.000000,
        "20" : 0.000000,
        "50" : 0.000000,
        "100" : 0.000000,
        "250" : 0.000000,
        "500" : 0.000000,
        "750" : 0.000000,
        "1000" : 0.000000
      },
      "latency_us" : {
        "2" : 0.000000,
        "4" : 0.000000,
        "10" : 0.000000,
        "20" : 0.010000,
        "50" : 0.010000,
        "100" : 83.323727,
        "250" : 16.650136,
        "500" : 0.022310,
        "750" : 0.010000,
        "1000" : 0.000000
      },
      "latency_ms" : {
        "2" : 0.000000,
        "4" : 0.000000,
        "10" : 0.000000,
        "20" : 0.000000,
        "50" : 0.000000,
        "100" : 0.000000,
        "250" : 0.000000,
        "500" : 0.000000,
        "750" : 0.000000,
        "1000" : 0.000000,
        "2000" : 0.000000,
        ">=2000" : 0.000000
      },
      "latency_depth" : 9,
      "latency_target" : 0,
      "latency_percentile" : 100.000000,
      "latency_window" : 0
    }
  ],
  "disk_util" : [
    {
      "name" : "nvme2n2",
      "read_ios" : 3729330,
      "write_ios" : 0,
      "read_merges" : 0,
      "write_merges" : 0,
      "read_ticks" : 338763,
      "write_ticks" : 0,
      "in_queue" : 338763,
      "util" : 99.825323
    }
  ]
}
