{
  "fio version" : "fio-3.28-261-gc3773-dirty",
  "timestamp" : 1648124411,
  "timestamp_ms" : 1648124411972,
  "time" : "Thu Mar 24 13:20:11 2022",
  "jobs" : [
    {
      "jobname" : "nvme2n2_none_4Ki_nummjobs-3",
      "groupid" : 0,
      "error" : 0,
      "eta" : 0,
      "elapsed" : 41,
      "job options" : {
        "name" : "nvme2n2_none_4Ki_nummjobs-3",
        "filename" : "/dev/nvme2n2",
        "direct" : "1",
        "size" : "3z",
        "offset_increment" : "3z",
        "ioengine" : "psync",
        "zonemode" : "zbd",
        "rw" : "write",
        "bs" : "4Ki",
        "runtime" : "30s",
        "numa_cpu_nodes" : "1",
        "ramp_time" : "10s",
        "numjobs" : "3",
        "percentile_list" : "50:95"
      },
      "read" : {
        "io_bytes" : 0,
        "io_kbytes" : 0,
        "bw_bytes" : 0,
        "bw" : 0,
        "iops" : 0.000000,
        "runtime" : 0,
        "total_ios" : 0,
        "short_ios" : 0,
        "drop_ios" : 0,
        "slat_ns" : {
          "min" : 0,
          "max" : 0,
          "mean" : 0.000000,
          "stddev" : 0.000000,
          "N" : 0
        },
        "clat_ns" : {
          "min" : 0,
          "max" : 0,
          "mean" : 0.000000,
          "stddev" : 0.000000,
          "N" : 0
        },
        "lat_ns" : {
          "min" : 0,
          "max" : 0,
          "mean" : 0.000000,
          "stddev" : 0.000000,
          "N" : 0
        },
        "bw_min" : 0,
        "bw_max" : 0,
        "bw_agg" : 0.000000,
        "bw_mean" : 0.000000,
        "bw_dev" : 0.000000,
        "bw_samples" : 0,
        "iops_min" : 0,
        "iops_max" : 0,
        "iops_mean" : 0.000000,
        "iops_stddev" : 0.000000,
        "iops_samples" : 0
      },
      "write" : {
        "io_bytes" : 6268604416,
        "io_kbytes" : 6121684,
        "bw_bytes" : 208946515,
        "bw" : 204049,
        "iops" : 51012.332922,
        "runtime" : 30001,
        "total_ios" : 1530421,
        "short_ios" : 0,
        "drop_ios" : 0,
        "slat_ns" : {
          "min" : 0,
          "max" : 0,
          "mean" : 0.000000,
          "stddev" : 0.000000,
          "N" : 0
        },
        "clat_ns" : {
          "min" : 16441,
          "max" : 14141707,
          "mean" : 58237.526708,
          "stddev" : 35515.205156,
          "N" : 1530421,
          "percentile" : {
            "50.000000" : 50432,
            "95.000000" : 111104
          }
        },
        "lat_ns" : {
          "min" : 16507,
          "max" : 14141770,
          "mean" : 58305.608218,
          "stddev" : 35515.236173,
          "N" : 1530421
        },
        "bw_min" : 198160,
        "bw_max" : 206745,
        "bw_agg" : 100.000000,
        "bw_mean" : 204182.350000,
        "bw_dev" : 468.500232,
        "bw_samples" : 180,
        "iops_min" : 49540,
        "iops_max" : 51686,
        "iops_mean" : 51045.366667,
        "iops_stddev" : 117.149065,
        "iops_samples" : 180
      },
      "trim" : {
        "io_bytes" : 0,
        "io_kbytes" : 0,
        "bw_bytes" : 0,
        "bw" : 0,
        "iops" : 0.000000,
        "runtime" : 0,
        "total_ios" : 0,
        "short_ios" : 0,
        "drop_ios" : 0,
        "slat_ns" : {
          "min" : 0,
          "max" : 0,
          "mean" : 0.000000,
          "stddev" : 0.000000,
          "N" : 0
        },
        "clat_ns" : {
          "min" : 0,
          "max" : 0,
          "mean" : 0.000000,
          "stddev" : 0.000000,
          "N" : 0
        },
        "lat_ns" : {
          "min" : 0,
          "max" : 0,
          "mean" : 0.000000,
          "stddev" : 0.000000,
          "N" : 0
        },
        "bw_min" : 0,
        "bw_max" : 0,
        "bw_agg" : 0.000000,
        "bw_mean" : 0.000000,
        "bw_dev" : 0.000000,
        "bw_samples" : 0,
        "iops_min" : 0,
        "iops_max" : 0,
        "iops_mean" : 0.000000,
        "iops_stddev" : 0.000000,
        "iops_samples" : 0
      },
      "sync" : {
        "total_ios" : 0,
        "lat_ns" : {
          "min" : 0,
          "max" : 0,
          "mean" : 0.000000,
          "stddev" : 0.000000,
          "N" : 0
        }
      },
      "job_runtime" : 90000,
      "usr_cpu" : 2.698889,
      "sys_cpu" : 5.114444,
      "ctx" : 1530428,
      "majf" : 0,
      "minf" : 109,
      "iodepth_level" : {
        "1" : 100.000000,
        "2" : 0.000000,
        "4" : 0.000000,
        "8" : 0.000000,
        "16" : 0.000000,
        "32" : 0.000000,
        ">=64" : 0.000000
      },
      "iodepth_submit" : {
        "0" : 0.000000,
        "4" : 100.000000,
        "8" : 0.000000,
        "16" : 0.000000,
        "32" : 0.000000,
        "64" : 0.000000,
        ">=64" : 0.000000
      },
      "iodepth_complete" : {
        "0" : 0.000000,
        "4" : 100.000000,
        "8" : 0.000000,
        "16" : 0.000000,
        "32" : 0.000000,
        "64" : 0.000000,
        ">=64" : 0.000000
      },
      "latency_ns" : {
        "2" : 0.000000,
        "4" : 0.000000,
        "10" : 0.000000,
        "20" : 0.000000,
        "50" : 0.000000,
        "100" : 0.000000,
        "250" : 0.000000,
        "500" : 0.000000,
        "750" : 0.000000,
        "1000" : 0.000000
      },
      "latency_us" : {
        "2" : 0.000000,
        "4" : 0.000000,
        "10" : 0.000000,
        "20" : 0.128723,
        "50" : 49.031280,
        "100" : 42.726152,
        "250" : 8.068695,
        "500" : 0.028946,
        "750" : 0.010000,
        "1000" : 0.010000
      },
      "latency_ms" : {
        "2" : 0.010000,
        "4" : 0.010000,
        "10" : 0.000000,
        "20" : 0.010000,
        "50" : 0.000000,
        "100" : 0.000000,
        "250" : 0.000000,
        "500" : 0.000000,
        "750" : 0.000000,
        "1000" : 0.000000,
        "2000" : 0.000000,
        ">=2000" : 0.000000
      },
      "latency_depth" : 1,
      "latency_target" : 0,
      "latency_percentile" : 100.000000,
      "latency_window" : 0
    }
  ],
  "disk_util" : [
    {
      "name" : "nvme2n2",
      "read_ios" : 48,
      "write_ios" : 2042581,
      "read_merges" : 0,
      "write_merges" : 0,
      "read_ticks" : 1,
      "write_ticks" : 112735,
      "in_queue" : 112736,
      "util" : 99.840303
    }
  ]
}
