{
  "fio version" : "fio-3.28-261-gc3773-dirty",
  "timestamp" : 1646738784,
  "timestamp_ms" : 1646738784197,
  "time" : "Tue Mar  8 12:26:24 2022",
  "jobs" : [
    {
      "jobname" : "nvme2n2_overwrite-rand_4Ki_queue-depth-8",
      "groupid" : 0,
      "error" : 0,
      "eta" : 0,
      "elapsed" : 41,
      "job options" : {
        "name" : "nvme2n2_overwrite-rand_4Ki_queue-depth-8",
        "filename" : "/dev/nvme2n2",
        "direct" : "1",
        "size" : "107374182400",
        "ioengine" : "libaio",
        "iodepth" : "8",
        "rw" : "randwrite",
        "bs" : "4Ki",
        "runtime" : "30s",
        "numa_cpu_nodes" : "1",
        "ramp_time" : "10s",
        "zonemode" : "zbd",
        "max_open_zones" : "4",
        "percentile_list" : "50:95"
      },
      "read" : {
        "io_bytes" : 0,
        "io_kbytes" : 0,
        "bw_bytes" : 0,
        "bw" : 0,
        "iops" : 0.000000,
        "runtime" : 0,
        "total_ios" : 0,
        "short_ios" : 0,
        "drop_ios" : 0,
        "slat_ns" : {
          "min" : 0,
          "max" : 0,
          "mean" : 0.000000,
          "stddev" : 0.000000,
          "N" : 0
        },
        "clat_ns" : {
          "min" : 0,
          "max" : 0,
          "mean" : 0.000000,
          "stddev" : 0.000000,
          "N" : 0
        },
        "lat_ns" : {
          "min" : 0,
          "max" : 0,
          "mean" : 0.000000,
          "stddev" : 0.000000,
          "N" : 0
        },
        "bw_min" : 0,
        "bw_max" : 0,
        "bw_agg" : 0.000000,
        "bw_mean" : 0.000000,
        "bw_dev" : 0.000000,
        "bw_samples" : 0,
        "iops_min" : 0,
        "iops_max" : 0,
        "iops_mean" : 0.000000,
        "iops_stddev" : 0.000000,
        "iops_samples" : 0
      },
      "write" : {
        "io_bytes" : 8664559616,
        "io_kbytes" : 8461484,
        "bw_bytes" : 288809026,
        "bw" : 282040,
        "iops" : 70509.783007,
        "runtime" : 30001,
        "total_ios" : 2115364,
        "short_ios" : 0,
        "drop_ios" : 0,
        "slat_ns" : {
          "min" : 1163,
          "max" : 56403,
          "mean" : 4448.482994,
          "stddev" : 2211.645104,
          "N" : 2115364
        },
        "clat_ns" : {
          "min" : 11776,
          "max" : 6670177,
          "mean" : 107661.308960,
          "stddev" : 59296.888977,
          "N" : 2115371,
          "percentile" : {
            "50.000000" : 96768,
            "95.000000" : 211968
          }
        },
        "lat_ns" : {
          "min" : 19839,
          "max" : 6674421,
          "mean" : 112219.414418,
          "stddev" : 58799.287751,
          "N" : 2115371
        },
        "bw_min" : 274992,
        "bw_max" : 285064,
        "bw_agg" : 100.000000,
        "bw_mean" : 282246.050000,
        "bw_dev" : 2283.316815,
        "bw_samples" : 60,
        "iops_min" : 68748,
        "iops_max" : 71266,
        "iops_mean" : 70561.416667,
        "iops_stddev" : 570.820946,
        "iops_samples" : 60
      },
      "trim" : {
        "io_bytes" : 0,
        "io_kbytes" : 0,
        "bw_bytes" : 0,
        "bw" : 0,
        "iops" : 0.000000,
        "runtime" : 0,
        "total_ios" : 0,
        "short_ios" : 0,
        "drop_ios" : 0,
        "slat_ns" : {
          "min" : 0,
          "max" : 0,
          "mean" : 0.000000,
          "stddev" : 0.000000,
          "N" : 0
        },
        "clat_ns" : {
          "min" : 0,
          "max" : 0,
          "mean" : 0.000000,
          "stddev" : 0.000000,
          "N" : 0
        },
        "lat_ns" : {
          "min" : 0,
          "max" : 0,
          "mean" : 0.000000,
          "stddev" : 0.000000,
          "N" : 0
        },
        "bw_min" : 0,
        "bw_max" : 0,
        "bw_agg" : 0.000000,
        "bw_mean" : 0.000000,
        "bw_dev" : 0.000000,
        "bw_samples" : 0,
        "iops_min" : 0,
        "iops_max" : 0,
        "iops_mean" : 0.000000,
        "iops_stddev" : 0.000000,
        "iops_samples" : 0
      },
      "sync" : {
        "total_ios" : 0,
        "lat_ns" : {
          "min" : 0,
          "max" : 0,
          "mean" : 0.000000,
          "stddev" : 0.000000,
          "N" : 0
        }
      },
      "job_runtime" : 30000,
      "usr_cpu" : 9.536667,
      "sys_cpu" : 23.413333,
      "ctx" : 2625698,
      "majf" : 0,
      "minf" : 37,
      "iodepth_level" : {
        "1" : 0.100000,
        "2" : 0.100000,
        "4" : 0.100000,
        "8" : 99.997353,
        "16" : 0.000000,
        "32" : 0.000000,
        ">=64" : 0.000000
      },
      "iodepth_submit" : {
        "0" : 0.000000,
        "4" : 100.000000,
        "8" : 0.000000,
        "16" : 0.000000,
        "32" : 0.000000,
        "64" : 0.000000,
        ">=64" : 0.000000
      },
      "iodepth_complete" : {
        "0" : 0.000000,
        "4" : 99.999953,
        "8" : 0.100000,
        "16" : 0.000000,
        "32" : 0.000000,
        "64" : 0.000000,
        ">=64" : 0.000000
      },
      "latency_ns" : {
        "2" : 0.000000,
        "4" : 0.000000,
        "10" : 0.000000,
        "20" : 0.000000,
        "50" : 0.000000,
        "100" : 0.000000,
        "250" : 0.000000,
        "500" : 0.000000,
        "750" : 0.000000,
        "1000" : 0.000000
      },
      "latency_us" : {
        "2" : 0.000000,
        "4" : 0.000000,
        "10" : 0.000000,
        "20" : 0.047415,
        "50" : 12.342888,
        "100" : 39.886516,
        "250" : 45.901698,
        "500" : 1.774068,
        "750" : 0.017727,
        "1000" : 0.013851
      },
      "latency_ms" : {
        "2" : 0.014513,
        "4" : 0.010000,
        "10" : 0.010000,
        "20" : 0.000000,
        "50" : 0.000000,
        "100" : 0.000000,
        "250" : 0.000000,
        "500" : 0.000000,
        "750" : 0.000000,
        "1000" : 0.000000,
        "2000" : 0.000000,
        ">=2000" : 0.000000
      },
      "latency_depth" : 8,
      "latency_target" : 0,
      "latency_percentile" : 100.000000,
      "latency_window" : 0
    }
  ],
  "disk_util" : [
    {
      "name" : "nvme2n2",
      "read_ios" : 0,
      "write_ios" : 1996237,
      "read_merges" : 0,
      "write_merges" : 824017,
      "read_ticks" : 0,
      "write_ticks" : 188191,
      "in_queue" : 188191,
      "util" : 99.810360
    }
  ]
}
